tsv_data_analytics_ext/__init__.py
tsv_data_analytics_ext/etlext.py
tsv_data_analytics_ext/graphext.py
tsv_data_analytics_ext/multi_thread_ext.py
tsv_data_analytics_ext-0.2.8.dist-info/METADATA
tsv_data_analytics_ext-0.2.8.dist-info/WHEEL
tsv_data_analytics_ext-0.2.8.dist-info/top_level.txt
tsv_data_analytics_ext-0.2.8.dist-info/RECORD
